Metadata-Version: 2.1
Name: paperwork-shell
Version: 2.2.4
Summary: Paperwork's shell interface
Author-email: Jerome Flesch <jflesch@openpaper.work>
License: GPL-3.0-or-later
License-File: LICENSE
Requires-Dist: openpaperwork-core
Requires-Dist: paperwork-backend
Requires-Dist: fabulous
Requires-Dist: rich
Provides-Extra: dev
Requires-Dist: pytest; extra == "dev"
Provides-Extra: lint
Requires-Dist: flake8; extra == "lint"
